gensyn-0.1.0.dist-info/METADATA
gensyn-0.1.0.dist-info/WHEEL
gensyn/__init__.py
gensyn-0.1.0.dist-info/RECORD
