Metadata-Version: 2.1
Name: gensyn
Version: 0.1.0
Summary: SDK for interacting with the Gensyn machine learning compute protocol.
Home-page: https://www.gensyn.ai/
Author-Email: Gensyn <developers@gensyn.ai>
Project-URL: Homepage, https://www.gensyn.ai/
Requires-Python: >=3.9
